<?xml version="1.0" encoding="UTF-8"?>
<!DOCTYPE plist PUBLIC "-//Apple//DTD PLIST 1.0//EN" "http://www.apple.com/DTDs/PropertyList-1.0.dtd"/>

<plist version="1.0">
    <dict>
        <key>ROOT</key>
        <array>
            <dict>
                <key>id</key>
                <string>102</string>
                <key>sprites</key>
                <array>
                    <string>44864</string>
                    <string>44292</string>
                    <string>34625</string>
                    <string>43089</string>
                    <string>44961</string>
                    <string>42167</string>
                    <string>44408</string>
                    <string>44905</string>
                    <string>44635</string>
                    <string>42741</string>
                    <string>44653</string>
                    <string>44400</string>
                    <string>44573</string>
                    <string>44579</string>
                    <string>44585</string>
                    <string>44591</string>
                    <string>44597</string>
                    <string>44611</string>
                    <string>44629</string>
                    <string>44647</string>
                    <string>43917</string>
                    <string>44309</string>
                    <string>43318</string>
                    <string>22119</string>
                    <string>45207</string>
                    <string>42056</string>
                    <string>35210</string>
                    <string>22158</string>
                    <string>34809</string>
                    <string>32472</string>
                    <string>34662</string>
                    <string>7792</string>
                    <string>23301</string>
                    <string>20544</string>
                    <string>20650</string>
                    <string>20657</string>
                    <string>20944</string>
                    <string>20935</string>
                    <string>20926</string>
                    <string>20917</string>
                    <string>20908</string>
                    <string>20897</string>
                    <string>20758</string>
                    <string>20747</string>
                    <string>34728</string>
                    <string>34723</string>
                    <string>43450</string>
                    <string>42254</string>
                    <string>43925</string>
                </array>
            </dict>
        </array>
    </dict>
</plist>
